mwk_traceback/__init__.py
mwk_traceback/custom_exc_tb.py
mwk_traceback/custom_warn.py
mwk_traceback-2.1.dist-info/LICENSE
mwk_traceback-2.1.dist-info/METADATA
mwk_traceback-2.1.dist-info/WHEEL
mwk_traceback-2.1.dist-info/top_level.txt
mwk_traceback-2.1.dist-info/RECORD
