Metadata-Version: 2.1
Name: mwk_traceback
Version: 2.1
Summary: Package for customizing exceptions and warnings messages.
Author-email: MWK <mjwk1020@gmail.com>
Project-URL: Homepage, https://github.com/MWKSolution/mwk-traceback
Classifier: Programming Language :: Python :: 3
Classifier: License :: OSI Approved :: MIT License
Classifier: Operating System :: OS Independent
Requires-Python: >=3.8
License-File: LICENSE
